miniProject_pkg/__init__.py
miniProjet_pkg_your_samiraoumami-0.0.2.dist-info/LICENSE
miniProjet_pkg_your_samiraoumami-0.0.2.dist-info/METADATA
miniProjet_pkg_your_samiraoumami-0.0.2.dist-info/WHEEL
miniProjet_pkg_your_samiraoumami-0.0.2.dist-info/top_level.txt
miniProjet_pkg_your_samiraoumami-0.0.2.dist-info/RECORD
