Metadata-Version: 2.1
Name: miniProjet-pkg-your-samiraoumami
Version: 0.0.2
Summary: Mini Projet GCP
Home-page: https://github.com/pypa/miniProjetSam
Author: samira oumami
Author-email: samira.oumami@gmail.com
License: UNKNOWN
Platform: UNKNOWN
